bpkcat/OWDuplicateChecker.py
bpkcat/OWSequenceChecker.py
bpkcat/__init__.py
bpkcat/icons/1.svg
bpkcat/icons/2.svg
bpkcat/icons/bpkcat-01.svg
bpkcat/icons/bpkcat.svg
bpkcat/icons/duplicate.svg
bpkcat/icons/sequence.svg
BPK_CAT-2.1.4.dist-info/METADATA
BPK_CAT-2.1.4.dist-info/WHEEL
BPK_CAT-2.1.4.dist-info/entry_points.txt
BPK_CAT-2.1.4.dist-info/top_level.txt
BPK_CAT-2.1.4.dist-info/RECORD
