Metadata-Version: 2.1
Name: BPK-CAT
Version: 2.1.4
Summary: Orange3 BPK Computer Assisted Audit Technique Tools (CAATT)
Home-page: https://www.bpk.go.id/
Author: BPK-RI
Author-email: eppid@bpk.go.id
